bluetooth.py
ev3dev2/__init__.py
ev3dev2/auto.py
ev3dev2/button.py
ev3dev2/console.py
ev3dev2/display.py
ev3dev2/led.py
ev3dev2/motor.py
ev3dev2/port.py
ev3dev2/power.py
ev3dev2/sound.py
ev3dev2/stopwatch.py
ev3dev2/unit.py
ev3dev2/version.py
ev3dev2/wheel.py
ev3dev2/_platform/__init__.py
ev3dev2/_platform/ev3.py
ev3dev2/fonts/__init__.py
ev3dev2/sensor/__init__.py
ev3dev2/sensor/lego.py
ev3dev2simulator/__init__.py
ev3dev2simulator/__main__.py
ev3dev2simulator/simulator.py
ev3dev2simulator/version.py
ev3dev2simulator/assets/images/arm.png
ev3dev2simulator/assets/images/arm_large.png
ev3dev2simulator/assets/images/body.png
ev3dev2simulator/assets/images/bottle.png
ev3dev2simulator/assets/images/brick.png
ev3dev2simulator/assets/images/color_sensor_black.png
ev3dev2simulator/assets/images/color_sensor_blue.png
ev3dev2simulator/assets/images/color_sensor_green.png
ev3dev2simulator/assets/images/color_sensor_red.png
ev3dev2simulator/assets/images/color_sensor_white.png
ev3dev2simulator/assets/images/color_sensor_yellow.png
ev3dev2simulator/assets/images/led_amber.png
ev3dev2simulator/assets/images/led_black.png
ev3dev2simulator/assets/images/led_green.png
ev3dev2simulator/assets/images/led_orange.png
ev3dev2simulator/assets/images/led_red.png
ev3dev2simulator/assets/images/led_yellow.png
ev3dev2simulator/assets/images/touch_sensor_left.png
ev3dev2simulator/assets/images/touch_sensor_rear.png
ev3dev2simulator/assets/images/touch_sensor_right.png
ev3dev2simulator/assets/images/ultrasonic_sensor_bottom.png
ev3dev2simulator/assets/images/ultrasonic_sensor_top.png
ev3dev2simulator/assets/images/wheel.png
ev3dev2simulator/config/__init__.py
ev3dev2simulator/config/config.py
ev3dev2simulator/config/config_checker.py
ev3dev2simulator/config/simulation_settings.yaml
ev3dev2simulator/config/robot_configurations/large_robot.yaml
ev3dev2simulator/config/robot_configurations/small_robot.yaml
ev3dev2simulator/config/world_configurations/config_large.yaml
ev3dev2simulator-2.0.10.dist-info/LICENSE.txt
ev3dev2simulator-2.0.10.dist-info/METADATA
ev3dev2simulator-2.0.10.dist-info/WHEEL
ev3dev2simulator-2.0.10.dist-info/entry_points.txt
ev3dev2simulator-2.0.10.dist-info/top_level.txt
ev3dev2simulator-2.0.10.dist-info/RECORD
