Metadata-Version: 2.1
Name: ev3dev2simulator
Version: 2.0.10
Summary: EV3 simulator for the ev3dev2 library
Author: Sam Jansen, Niels Okker
Author-email: Harco Kuppens <h.kuppens@cs.ru.nl>
License: The MIT License (MIT)
Project-URL: Homepage, https://github.com/ev3dev-python-tools/ev3dev2simulator
Keywords: IDE,education,programming,EV3,mindstorms,lego
Classifier: Environment :: MacOS X
Classifier: Environment :: Win32 (MS Windows)
Classifier: Environment :: X11 Applications
Classifier: Intended Audience :: Developers
Classifier: Intended Audience :: Education
Classifier: Intended Audience :: End Users/Desktop
Classifier: License :: OSI Approved :: MIT License
Classifier: Natural Language :: English
Classifier: Operating System :: MacOS
Classifier: Operating System :: Microsoft :: Windows
Classifier: Operating System :: POSIX :: Linux
Classifier: Programming Language :: Python :: 3
Classifier: Topic :: Education
Classifier: Topic :: Software Development
License-File: LICENSE.txt
Requires-Dist: ev3devlogging
Requires-Dist: arcade ==2.6.16
Requires-Dist: simpleaudio-patched
Requires-Dist: py3-tts
Requires-Dist: numpy
Requires-Dist: strictyaml
Requires-Dist: pylint ==2.5.3
Requires-Dist: pyobjc ==9.2 ; platform_system == "Darwin"
